stepper_motor_controller/__init__.py
stepper_motor_controller/config.py
stepper_motor_controller/node.py
stepper_motor_controller/proxy.py
stepper_motor_controller/state.py
stepper_motor_controller/Arduino/library/StepperMotorController.zip
stepper_motor_controller/Arduino/library/StepperMotorController/library.properties
stepper_motor_controller/Arduino/library/StepperMotorController/src/StepperMotorController.h
stepper_motor_controller/Arduino/library/StepperMotorController/src/StepperMotorController/CommandProcessor.h
stepper_motor_controller/Arduino/library/StepperMotorController/src/StepperMotorController/Commands.h
stepper_motor_controller/Arduino/library/StepperMotorController/src/StepperMotorController/Properties.h
stepper_motor_controller/Arduino/library/StepperMotorController/src/StepperMotorController/config_pb.c
stepper_motor_controller/Arduino/library/StepperMotorController/src/StepperMotorController/config_pb.h
stepper_motor_controller/Arduino/library/StepperMotorController/src/StepperMotorController/state_pb.c
stepper_motor_controller/Arduino/library/StepperMotorController/src/StepperMotorController/state_pb.h
stepper_motor_controller/Arduino/stepper_motor_controller/Node.cpp
stepper_motor_controller/Arduino/stepper_motor_controller/Node.h
stepper_motor_controller/Arduino/stepper_motor_controller/NodeCommandProcessor.h
stepper_motor_controller/Arduino/stepper_motor_controller/RPCBuffer.h
stepper_motor_controller/Arduino/stepper_motor_controller/RPCBuffer.ht
stepper_motor_controller/Arduino/stepper_motor_controller/SConscript
stepper_motor_controller/Arduino/stepper_motor_controller/config.options
stepper_motor_controller/Arduino/stepper_motor_controller/config.proto
stepper_motor_controller/Arduino/stepper_motor_controller/state.proto
stepper_motor_controller/Arduino/stepper_motor_controller/stepper_motor_controller.ino
stepper_motor_controller/Arduino/stepper_motor_controller/stepper_motor_controller_config_validate.h
stepper_motor_controller-0.3.dist-info/DESCRIPTION.rst
stepper_motor_controller-0.3.dist-info/METADATA
stepper_motor_controller-0.3.dist-info/RECORD
stepper_motor_controller-0.3.dist-info/WHEEL
stepper_motor_controller-0.3.dist-info/metadata.json
stepper_motor_controller-0.3.dist-info/top_level.txt
