Metadata-Version: 2.0
Name: stepper-motor-controller
Version: 0.3
Summary: Stepper motorcontroller based on the Arduino base node RPC framework.
Home-page: http://github.com/sci-bots/stepper-motor-controller.git
Author: Ryan Fobel
Author-email: ryan@sci-bots.com
License: GPLv2
Platform: UNKNOWN
Requires-Dist: base-node-rpc (>=0.17)
